fasthep_logging/__init__.py
fasthep_logging/_logging.py
fasthep_logging/_version.py
fasthep_logging/_version.pyi
fasthep_logging/py.typed
fasthep_logging-2024.6.1.dist-info/METADATA
fasthep_logging-2024.6.1.dist-info/WHEEL
fasthep_logging-2024.6.1.dist-info/licenses/LICENSE
fasthep_logging-2024.6.1.dist-info/RECORD
