Metadata-Version: 2.3
Name: fasthep_logging
Version: 2024.6.1
Summary: Enhanced logging for the FAST-HEP toolkit
Project-URL: homepage, https://github.com/FAST-HEP/fasthep-logging
Project-URL: Bug Tracker, https://github.com/FAST-HEP/fasthep-logging/issues
Project-URL: Discussions, https://github.com/FAST-HEP/fasthep-logging/discussions
Project-URL: Changelog, https://github.com/FAST-HEP/fasthep-logging/releases
Author-email: Luke Kreczko <kreczko@cern.ch>
Maintainer-email: The FAST-HEP admins <fast-hep@cern.ch>
License-File: LICENSE
Classifier: Development Status :: 1 - Planning
Classifier: Intended Audience :: Developers
Classifier: Intended Audience :: Science/Research
Classifier: License :: OSI Approved :: Apache Software License
Classifier: License :: OSI Approved :: BSD License
Classifier: Operating System :: OS Independent
Classifier: Programming Language :: Python
Classifier: Programming Language :: Python :: 3
Classifier: Programming Language :: Python :: 3.9
Classifier: Programming Language :: Python :: 3.10
Classifier: Programming Language :: Python :: 3.11
Classifier: Programming Language :: Python :: 3.12
Classifier: Topic :: Scientific/Engineering
Requires-Python: >=3.9
Requires-Dist: rich>=10.12.0
Provides-Extra: dev
Requires-Dist: pytest>=6; extra == 'dev'
Provides-Extra: docs
Requires-Dist: myst-parser>=0.13; extra == 'docs'
Requires-Dist: sphinx-book-theme>=0.1.0; extra == 'docs'
Requires-Dist: sphinx-copybutton; extra == 'docs'
Requires-Dist: sphinx>=4.0; extra == 'docs'
Provides-Extra: test
Requires-Dist: pytest>=6; extra == 'test'
